odoo/addons/sale_missing_tracking_tier_validation/README.rst
odoo/addons/sale_missing_tracking_tier_validation/__init__.py
odoo/addons/sale_missing_tracking_tier_validation/__manifest__.py
odoo/addons/sale_missing_tracking_tier_validation/i18n/es.po
odoo/addons/sale_missing_tracking_tier_validation/i18n/sale_missing_tracking_tier_validation.pot
odoo/addons/sale_missing_tracking_tier_validation/models/__init__.py
odoo/addons/sale_missing_tracking_tier_validation/models/sale_missing_tracking_exception.py
odoo/addons/sale_missing_tracking_tier_validation/models/tier_definition.py
odoo/addons/sale_missing_tracking_tier_validation/readme/CONFIGURE.rst
odoo/addons/sale_missing_tracking_tier_validation/readme/CONTRIBUTORS.rst
odoo/addons/sale_missing_tracking_tier_validation/readme/DESCRIPTION.rst
odoo/addons/sale_missing_tracking_tier_validation/readme/USAGE.rst
odoo/addons/sale_missing_tracking_tier_validation/static/description/icon.png
odoo/addons/sale_missing_tracking_tier_validation/static/description/index.html
odoo/addons/sale_missing_tracking_tier_validation/tests/__init__.py
odoo/addons/sale_missing_tracking_tier_validation/tests/test_sale_missing_tracking_tier_validation.py
odoo/addons/sale_missing_tracking_tier_validation/views/sale_missing_tracking_exception_view.xml
odoo_addon_sale_missing_tracking_tier_validation-15.0.1.0.0.4.dist-info/METADATA
odoo_addon_sale_missing_tracking_tier_validation-15.0.1.0.0.4.dist-info/WHEEL
odoo_addon_sale_missing_tracking_tier_validation-15.0.1.0.0.4.dist-info/top_level.txt
odoo_addon_sale_missing_tracking_tier_validation-15.0.1.0.0.4.dist-info/RECORD
